MANIFEST.in
README.txt
setup.py
Products/__init__.py
Products.TIDStorage.egg-info/PKG-INFO
Products.TIDStorage.egg-info/SOURCES.txt
Products.TIDStorage.egg-info/dependency_links.txt
Products.TIDStorage.egg-info/entry_points.txt
Products.TIDStorage.egg-info/namespace_packages.txt
Products.TIDStorage.egg-info/not-zip-safe
Products.TIDStorage.egg-info/requires.txt
Products.TIDStorage.egg-info/top_level.txt
Products/TIDStorage/CHANGES
Products/TIDStorage/ExchangeProtocol.py
Products/TIDStorage/README
Products/TIDStorage/TIDClient.py
Products/TIDStorage/VERSION.txt
Products/TIDStorage/ZEOClientStorage.py
Products/TIDStorage/__init__.py
Products/TIDStorage/transaction_transaction.py
Products/TIDStorage/bin/__init__.py
Products/TIDStorage/bin/tidstorage.py
Products/TIDStorage/repozo/__init__.py
Products/TIDStorage/repozo/repozo_tidstorage.py
Products/TIDStorage/repozo/restore_tidstorage.py
Products/TIDStorage/repozo/sample_configuration.py
Products/TIDStorage/tests/__init__.py
Products/TIDStorage/tests/testTIDServer.py
Products/TIDStorage/utils/__init__.py
Products/TIDStorage/utils/check_tid_log.py
Products/TIDStorage/utils/dump_tid_dict.py
Products/TIDStorage/utils/tid_log_to_full.py