Metadata-Version: 1.1
Name: Products.TIDStorage
Version: 5.4.9
Summary: TIDStorage Product provides a way to have consistent backups when running a multi-storage instance (only ZEO is supported at the moment).
Home-page: https://svn.erp5.org/repos/public/erp5/trunk/utils/Products.TIDStorage/
Author: Vincent Pelletier
Author-email: vincent@nexedi.com
License: UNKNOWN
Keywords: Zope TIDStorage
Platform: UNKNOWN
Classifier: Framework :: Zope2
Classifier: Operating System :: OS Independent
